{
  "ID": "e9ca50cd-0e77-483c-8593-393ae279a74e",
  "Version": "3.10.0.0",
  "Name": "vsRankGetItem",
  "Content": {
    "Content": {
      "Animation": {
        "Duration": 0,
        "Speed": 1.0,
        "Timelines": [],
        "ctype": "TimelineActionData"
      },
      "AnimationList": [],
      "ObjectData": {
        "Tag": 204,
        "Children": [
          {
            "ClipAble": false,
            "BackColorAlpha": 102,
            "SingleColor": {
              "R": 150,
              "G": 200
            },
            "FirstColor": {
              "R": 150,
              "G": 200
            },
            "EndColor": {},
            "ColorVector": {
              "ScaleY": 1.0
            },
            "Scale9Width": 1,
            "Scale9Height": 1,
            "AnchorPoint": {},
            "Position": {
              "X": 0.0,
              "Y": 0.0
            },
            "Scale": {
              "ScaleX": 1.0,
              "ScaleY": 1.0
            },
            "CColor": {},
            "IconVisible": false,
            "PrePosition": {
              "X": 0.0,
              "Y": 0.0
            },
            "PreSize": {
              "X": 1.0,
              "Y": 0.9615
            },
            "TopMargin": 4.0,
            "Tag": 140,
            "Children": [
              {
                "FileData": {
                  "Type": "MarkedSubImage",
                  "Path": "common/a/a_015.png",
                  "Plist": "common/a/box.plist"
                },
                "Scale9OriginX": 171,
                "Scale9OriginY": 41,
                "Scale9Width": 177,
                "Scale9Height": 45,
                "AnchorPoint": {
                  "ScaleX": 0.5,
                  "ScaleY": 0.5
                },
                "Position": {
                  "X": 259.4299,
                  "Y": 52.0577
                },
                "Scale": {
                  "ScaleX": 1.0,
                  "ScaleY": 1.0
                },
                "CColor": {},
                "IconVisible": false,
                "PrePosition": {
                  "X": 0.4999,
                  "Y": 0.5206
                },
                "PreSize": {
                  "X": 1.0,
                  "Y": 1.0
                },
                "LeftMargin": -0.0701,
                "RightMargin": 0.0701,
                "TopMargin": -2.0577,
                "BottomMargin": 2.0577,
                "Tag": 231,
                "Children": [
                  {
                    "FileData": {
                      "Type": "MarkedSubImage",
                      "Path": "common/c/c_037_2.png",
                      "Plist": "common/c/button.plist"
                    },
                    "Scale9OriginX": 39,
                    "Scale9OriginY": 39,
                    "Scale9Width": 10,
                    "Scale9Height": 10,
                    "AnchorPoint": {
                      "ScaleX": 0.5,
                      "ScaleY": 0.5
                    },
                    "Position": {
                      "X": 313.9182,
                      "Y": 48.7188
                    },
                    "Scale": {
                      "ScaleX": 0.8418,
                      "ScaleY": 0.8418
                    },
                    "CColor": {},
                    "IconVisible": false,
                    "PrePosition": {
                      "X": 0.6049,
                      "Y": 0.4872
                    },
                    "PreSize": {
                      "X": 0.1696,
                      "Y": 0.88
                    },
                    "LeftMargin": 269.9182,
                    "RightMargin": 161.0818,
                    "TopMargin": 7.2812,
                    "BottomMargin": 4.7188,
                    "Tag": 2942,
                    "Children": [
                      {
                        "FileData": {
                          "Type": "MarkedSubImage",
                          "Path": "common/i/i_007.png",
                          "Plist": "common/i/icon.plist"
                        },
                        "Scale9OriginX": 29,
                        "Scale9OriginY": 29,
                        "Scale9Width": 6,
                        "Scale9Height": 18,
                        "TouchEnable": true,
                        "AnchorPoint": {
                          "ScaleX": 0.5,
                          "ScaleY": 0.5
                        },
                        "Position": {
                          "X": 44.3473,
                          "Y": 43.1331
                        },
                        "Scale": {
                          "ScaleX": 0.8,
                          "ScaleY": 0.8
                        },
                        "CColor": {},
                        "IconVisible": false,
                        "PrePosition": {
                          "X": 0.5039,
                          "Y": 0.4901
                        },
                        "PreSize": {
                          "X": 0.7273,
                          "Y": 0.8636
                        },
                        "LeftMargin": 12.3473,
                        "RightMargin": 11.6527,
                        "TopMargin": 6.8669,
                        "BottomMargin": 5.1331,
                        "Tag": 2943,
                        "ActionTag": 1620641042,
                        "Size": {
                          "X": 64.0,
                          "Y": 76.0
                        },
                        "Name": "bagItemRGIcon1",
                        "ctype": "ImageViewObjectData"
                      },
                      {
                        "FontSize": 20,
                        "LabelText": "1000",
                        "OutlineColor": {
                          "G": 0,
                          "B": 0
                        },
                        "ShadowColor": {
                          "R": 110,
                          "G": 110,
                          "B": 110
                        },
                        "ShadowOffsetX": 2.0,
                        "ShadowOffsetY": -2.0,
                        "AnchorPoint": {
                          "ScaleX": 0.5,
                          "ScaleY": 0.5
                        },
                        "Position": {
                          "X": 58.4156,
                          "Y": 17.1818
                        },
                        "Scale": {
                          "ScaleX": 1.0,
                          "ScaleY": 1.0
                        },
                        "RotationSkewX": 1.5844,
                        "RotationSkewY": 1.5844,
                        "CColor": {},
                        "IconVisible": false,
                        "PrePosition": {
                          "X": 0.6638,
                          "Y": 0.1952
                        },
                        "PreSize": {
                          "X": 0.4545,
                          "Y": 0.2273
                        },
                        "LeftMargin": 38.4156,
                        "RightMargin": 9.5844,
                        "TopMargin": 60.8182,
                        "BottomMargin": 7.1818,
                        "Tag": 1928,
                        "ActionTag": -1043061139,
                        "Size": {
                          "X": 40.0,
                          "Y": 20.0
                        },
                        "Name": "textRankGet_Num1",
                        "ctype": "TextObjectData"
                      },
                      {
                        "FileData": {
                          "Type": "MarkedSubImage",
                          "Path": "common/i/i_040.png",
                          "Plist": "common/i/icon.plist"
                        },
                        "Scale9OriginX": 7,
                        "Scale9OriginY": 9,
                        "Scale9Width": 20,
                        "Scale9Height": 9,
                        "AnchorPoint": {
                          "ScaleX": 0.5,
                          "ScaleY": 0.5
                        },
                        "Position": {
                          "X": 24.6043,
                          "Y": 59.726
                        },
                        "Scale": {
                          "ScaleX": 1.0,
                          "ScaleY": 1.0
                        },
                        "CColor": {},
                        "IconVisible": false,
                        "PrePosition": {
                          "X": 0.2796,
                          "Y": 0.6787
                        },
                        "PreSize": {
                          "X": 0.2614,
                          "Y": 0.3182
                        },
                        "LeftMargin": 13.1043,
                        "RightMargin": 51.8957,
                        "TopMargin": 14.274,
                        "BottomMargin": 45.726,
                        "Tag": 1929,
                        "ActionTag": -484699078,
                        "Size": {
                          "X": 23.0,
                          "Y": 28.0
                        },
                        "VisibleForFrame": false,
                        "Name": "bagRGPieces1",
                        "ctype": "ImageViewObjectData"
                      }
                    ],
                    "ActionTag": 1337534972,
                    "Size": {
                      "X": 88.0,
                      "Y": 88.0
                    },
                    "Name": "bagItemRGBg1",
                    "ctype": "ImageViewObjectData"
                  },
                  {
                    "FileData": {
                      "Type": "MarkedSubImage",
                      "Path": "common/c/c_037_2.png",
                      "Plist": "common/c/button.plist"
                    },
                    "Scale9OriginX": 39,
                    "Scale9OriginY": 39,
                    "Scale9Width": 10,
                    "Scale9Height": 10,
                    "AnchorPoint": {
                      "ScaleX": 0.5,
                      "ScaleY": 0.5
                    },
                    "Position": {
                      "X": 402.1584,
                      "Y": 49.5106
                    },
                    "Scale": {
                      "ScaleX": 0.8418,
                      "ScaleY": 0.8418
                    },
                    "CColor": {},
                    "IconVisible": false,
                    "PrePosition": {
                      "X": 0.7749,
                      "Y": 0.4951
                    },
                    "PreSize": {
                      "X": 0.1696,
                      "Y": 0.88
                    },
                    "LeftMargin": 358.1584,
                    "RightMargin": 72.8416,
                    "TopMargin": 6.4894,
                    "BottomMargin": 5.5106,
                    "Tag": 2671,
                    "Children": [
                      {
                        "FileData": {
                          "Type": "MarkedSubImage",
                          "Path": "common/i/i_007.png",
                          "Plist": "common/i/icon.plist"
                        },
                        "Scale9OriginX": 29,
                        "Scale9OriginY": 29,
                        "Scale9Width": 6,
                        "Scale9Height": 18,
                        "TouchEnable": true,
                        "AnchorPoint": {
                          "ScaleX": 0.5,
                          "ScaleY": 0.5
                        },
                        "Position": {
                          "X": 44.3473,
                          "Y": 43.1331
                        },
                        "Scale": {
                          "ScaleX": 0.8,
                          "ScaleY": 0.8
                        },
                        "CColor": {},
                        "IconVisible": false,
                        "PrePosition": {
                          "X": 0.5039,
                          "Y": 0.4901
                        },
                        "PreSize": {
                          "X": 0.7273,
                          "Y": 0.8636
                        },
                        "LeftMargin": 12.3473,
                        "RightMargin": 11.6527,
                        "TopMargin": 6.8669,
                        "BottomMargin": 5.1331,
                        "Tag": 2672,
                        "ActionTag": -1205847794,
                        "Size": {
                          "X": 64.0,
                          "Y": 76.0
                        },
                        "Name": "bagItemRGIcon2",
                        "ctype": "ImageViewObjectData"
                      },
                      {
                        "FontSize": 20,
                        "LabelText": "1000",
                        "OutlineColor": {
                          "G": 0,
                          "B": 0
                        },
                        "ShadowColor": {
                          "R": 110,
                          "G": 110,
                          "B": 110
                        },
                        "ShadowOffsetX": 2.0,
                        "ShadowOffsetY": -2.0,
                        "AnchorPoint": {
                          "ScaleX": 0.5,
                          "ScaleY": 0.5
                        },
                        "Position": {
                          "X": 58.4156,
                          "Y": 17.1818
                        },
                        "Scale": {
                          "ScaleX": 1.0,
                          "ScaleY": 1.0
                        },
                        "RotationSkewX": 1.5844,
                        "RotationSkewY": 1.5844,
                        "CColor": {},
                        "IconVisible": false,
                        "PrePosition": {
                          "X": 0.6638,
                          "Y": 0.1952
                        },
                        "PreSize": {
                          "X": 0.4545,
                          "Y": 0.2273
                        },
                        "LeftMargin": 38.4156,
                        "RightMargin": 9.5844,
                        "TopMargin": 60.8182,
                        "BottomMargin": 7.1818,
                        "Tag": 2673,
                        "ActionTag": 2085366673,
                        "Size": {
                          "X": 40.0,
                          "Y": 20.0
                        },
                        "Name": "textRankGet_Num2",
                        "ctype": "TextObjectData"
                      },
                      {
                        "FileData": {
                          "Type": "MarkedSubImage",
                          "Path": "common/i/i_040.png",
                          "Plist": "common/i/icon.plist"
                        },
                        "Scale9OriginX": 7,
                        "Scale9OriginY": 9,
                        "Scale9Width": 20,
                        "Scale9Height": 9,
                        "AnchorPoint": {
                          "ScaleX": 0.5,
                          "ScaleY": 0.5
                        },
                        "Position": {
                          "X": 24.6043,
                          "Y": 59.726
                        },
                        "Scale": {
                          "ScaleX": 1.0,
                          "ScaleY": 1.0
                        },
                        "CColor": {},
                        "IconVisible": false,
                        "PrePosition": {
                          "X": 0.2796,
                          "Y": 0.6787
                        },
                        "PreSize": {
                          "X": 0.2614,
                          "Y": 0.3182
                        },
                        "LeftMargin": 13.1043,
                        "RightMargin": 51.8957,
                        "TopMargin": 14.274,
                        "BottomMargin": 45.726,
                        "Tag": 2674,
                        "ActionTag": -877108915,
                        "Size": {
                          "X": 23.0,
                          "Y": 28.0
                        },
                        "VisibleForFrame": false,
                        "Name": "bagRGPieces2",
                        "ctype": "ImageViewObjectData"
                      }
                    ],
                    "ActionTag": 209475037,
                    "Size": {
                      "X": 88.0,
                      "Y": 88.0
                    },
                    "Name": "bagItemRGBg2",
                    "ctype": "ImageViewObjectData"
                  }
                ],
                "ActionTag": -1197664771,
                "Size": {
                  "X": 519.0,
                  "Y": 100.0
                },
                "Name": "itemBg",
                "ctype": "ImageViewObjectData"
              },
              {
                "FontSize": 20,
                "LabelText": "第1~100000名",
                "FontResource": {
                  "Type": "Normal",
                  "Path": "font/fnt_text.TTF",
                  "Plist": ""
                },
                "OutlineSize": 2,
                "OutlineColor": {
                  "R": 0,
                  "G": 30,
                  "B": 0
                },
                "OutlineEnabled": true,
                "ShadowColor": {
                  "R": 110,
                  "G": 110,
                  "B": 110
                },
                "ShadowOffsetX": 2.0,
                "ShadowOffsetY": -2.0,
                "AnchorPoint": {
                  "ScaleX": 0.5,
                  "ScaleY": 0.5
                },
                "Position": {
                  "X": 102.7707,
                  "Y": 51.7577
                },
                "Scale": {
                  "ScaleX": 1.0,
                  "ScaleY": 1.0
                },
                "CColor": {
                  "R": 213,
                  "G": 238,
                  "B": 144
                },
                "IconVisible": false,
                "PrePosition": {
                  "X": 0.198,
                  "Y": 0.5176
                },
                "PreSize": {
                  "X": 0.2582,
                  "Y": 0.27
                },
                "LeftMargin": 35.7707,
                "RightMargin": 349.2293,
                "TopMargin": 34.7423,
                "BottomMargin": 38.2577,
                "Tag": 1927,
                "ActionTag": 189248629,
                "Size": {
                  "X": 134.0,
                  "Y": 27.0
                },
                "Name": "textRankGet",
                "ctype": "TextObjectData"
              }
            ],
            "ActionTag": 385852981,
            "Size": {
              "X": 519.0,
              "Y": 100.0
            },
            "Name": "item",
            "ctype": "PanelObjectData"
          }
        ],
        "Size": {
          "X": 519.0,
          "Y": 104.0
        },
        "Name": "Layer",
        "ctype": "LayerObjectData"
      },
      "UsedResources": [
        "common/a/box.plist",
        "common/a/box.png",
        "common/c/button.plist",
        "common/c/button.png",
        "common/i/icon.plist",
        "common/i/icon.png",
        "font/fnt_text.TTF"
      ],
      "ctype": "GameFileData"
    }
  },
  "Type": "Layer"
}